{
  "arduino": [
    {
      "id": "led_1",
      "status": "_bat",
      "date": "2020-09-03T08:44:44.399Z"
    },
    {
      "id": "led_2",
      "status": "_bat",
      "date": "2020-09-03T08:17:15.614Z"
    },
    {
      "id": "led_3",
      "status": "_bat",
      "date": "2020-09-03T08:17:16.580Z"
    },
    {
      "id": "led_4",
      "status": "_bat",
      "date": "2020-09-03T08:17:17.396Z"
    },
    {
      "id": "fan_1",
      "status": "_bat",
      "date": "2020-09-03T08:17:18.446Z"
    },
    {
      "id": "fan_2",
      "status": "_bat",
      "date": "2020-09-03T08:18:19.671Z"
    }
  ],
  "arduino_history": [
    {
      "id": "led_1",
      "status": "_bat",
      "date": "2020-09-04T07:32:15.869Z"
    }
  ],
  "words": []
}